{
    "number": "01",
    "year": 2024,
    "structure": {
        "variable-name": "depot_locations*",
        "git-root": true,
        "compulsory": [
            "country.py",
            "execution_time.py",
            "test_country.py",
            "utilities.py"
        ],
        "optional": [
            "deciding_depot_locations.ipynb",
            "plotting_utilities.py"
        ],
        "report": {
            "compulsory": [
                "report.md",
                "nna_execution_times.png"
            ],
            "optional": [
                "AIUsage.md",
                "Feedback.md"
            ]
        },
        "data": {
            "optional": [
                "locations.csv"
            ],
            "data-file-types": [
                "*.csv"
            ]
        },
        ".github": {
            "data-file-types": [
                "*"
            ]
        }
    }
}
